{
  "20036": [
    {
      "name": "Scott",
      "day": [
        false,
        false,
        false,
        false,
        false,
        false,
        false
      ]
    },
    {
      "name": "Larry",
      "day": [
        false,
        false,
        false,
        false,
        false,
        false,
        false
      ]
    },
    {
      "name": "Tim",
      "day": [
        false,
        false,
        false,
        false,
        false,
        false,
        false
      ]
    }
  ]
}